sparkdataset/__init__.py
sparkdataset/datasets_handler.py
sparkdataset/dump_data.py
sparkdataset/locate_datasets.py
sparkdataset/resources.tar.gz
sparkdataset/support.py
sparkdataset/utils/__init__.py
sparkdataset/utils/html2text.py
sparkdataset-1.0.0.dist-info/LICENSE
sparkdataset-1.0.0.dist-info/METADATA
sparkdataset-1.0.0.dist-info/WHEEL
sparkdataset-1.0.0.dist-info/top_level.txt
sparkdataset-1.0.0.dist-info/RECORD
