Metadata-Version: 2.1
Name: sparkdataset
Version: 1.0.0
Summary: Provides instant access to many popular datasets right from Pyspark (in dataframe structure).
Home-page: https://github.com/Spratiher9/SparkDataset
Author: Souvik Pratiher
Author-email: spratiher9@gmail.com
License: MIT
Download-URL: https://github.com/Spratiher9/SparkDataset/archive/refs/tags/1.0.0.tar.gz
Keywords: Spark,Apache Spark,benchmarking,data,datasets,standard data
Platform: UNKNOWN
Classifier: Development Status :: 5 - Production/Stable
Classifier: Intended Audience :: Developers
Classifier: Topic :: Software Development
Classifier: Programming Language :: Python :: 3.8
Classifier: Programming Language :: Python :: 3.10
License-File: LICENSE
Requires-Dist: pandas
Requires-Dist: pyspark (==3.1.2)
